proto_py/__init__.py
proto_py/badSituations.py
proto_py/baseCommands.py
proto_py/baseCommandsImpl.py
proto_py/commandList.py
proto_py/config.py
proto_py/connection.py
proto_py/connectionPool.py
proto_py/const.py
proto_py/flags.py
proto_py/handlerPool.py
proto_py/logger.py
proto_py/message.py
proto_py/messagePool.py
proto_py/tcpServer.py
proto_py/tcpSocket.py
proto_py/tcpWorker.py
proto_py/tools.py
proto_py-1.1.3.dist-info/DESCRIPTION.rst
proto_py-1.1.3.dist-info/METADATA
proto_py-1.1.3.dist-info/RECORD
proto_py-1.1.3.dist-info/WHEEL
proto_py-1.1.3.dist-info/metadata.json
proto_py-1.1.3.dist-info/top_level.txt
