Metadata-Version: 2.0
Name: proto-py
Version: 1.1.3
Summary: package with proto_py for PointOfView
Home-page: https://github.com/TochkaAI/proto_py
License: UNKNOWN
Platform: UNKNOWN
Classifier: Programming Language :: Python :: 3
Classifier: License :: OSI Approved :: MIT License
Classifier: Operating System :: OS Independent
Requires-Python: >=3.6
